coverage_checker_zcool/__init__.py
coverage_checker_zcool/classes.py
coverage_checker_zcool-0.0.1.dist-info/METADATA
coverage_checker_zcool-0.0.1.dist-info/WHEEL
coverage_checker_zcool-0.0.1.dist-info/top_level.txt
coverage_checker_zcool-0.0.1.dist-info/RECORD
